db_populator/__init__.py
db_populator/db_populator_conf.py
db_populator/management/commands/populate_db.py
db_populator/modified_ddf/__init__.py
db_populator/modified_ddf/ddf.py
db_populator/modified_ddf/decorators.py
db_populator/modified_ddf/django_helper.py
db_populator/modified_ddf/global_settings.py
db_populator/modified_ddf/settings.py
db_populator/modified_ddf/fixture_algorithms/__init__.py
db_populator/modified_ddf/fixture_algorithms/default_fixture.py
db_populator/modified_ddf/fixture_algorithms/random_fixture.py
db_populator/modified_ddf/fixture_algorithms/sequential_fixture.py
db_populator/modified_ddf/fixture_algorithms/unique_random_fixture.py
db_populator-1.0.1.dist-info/DESCRIPTION.rst
db_populator-1.0.1.dist-info/METADATA
db_populator-1.0.1.dist-info/metadata.json
db_populator-1.0.1.dist-info/RECORD
db_populator-1.0.1.dist-info/top_level.txt
db_populator-1.0.1.dist-info/WHEEL
