Metadata-Version: 2.0
Name: db-populator
Version: 1.0.1
Summary: Port of DDF for algorithmically creating an initial dataset
Home-page: http://github.com/slensgra/db_populator
Author: Samuel Lensgraf
Author-email: sam.lensgraf@gmail.com
License: MIT
Keywords: django,database,graph
Platform: UNKNOWN
Classifier: Intended Audience :: Developers
Classifier: Operating System :: OS Independent
Classifier: Programming Language :: Python :: 3
Classifier: Topic :: Software Development :: Libraries :: Python Modules
Classifier: Environment :: Web Environment
Classifier: Framework :: Django
Requires-Dist: django (>=1.4)
